llama_index/response_synthesizers/google/__init__.py
llama_index/response_synthesizers/google/base.py
flying_delta_response_synthesizers_google-0.1.0.dist-info/METADATA
flying_delta_response_synthesizers_google-0.1.0.dist-info/WHEEL
flying_delta_response_synthesizers_google-0.1.0.dist-info/RECORD
